thermoextrap/__init__.py
thermoextrap/adaptive_interp.py
thermoextrap/beta.py
thermoextrap/data.py
thermoextrap/idealgas.py
thermoextrap/lnpi.py
thermoextrap/models.py
thermoextrap/py.typed
thermoextrap/recursive_interp.py
thermoextrap/stack.py
thermoextrap/volume.py
thermoextrap/volume_idealgas.py
thermoextrap/core/__init__.py
thermoextrap/core/_attrs_utils.py
thermoextrap/core/_deprecate.py
thermoextrap/core/_imports.py
thermoextrap/core/compat.py
thermoextrap/core/docstrings.py
thermoextrap/core/sputils.py
thermoextrap/core/typing.py
thermoextrap/core/typing_compat.py
thermoextrap/core/validate.py
thermoextrap/core/xrutils.py
thermoextrap/gpr_active/__init__.py
thermoextrap/gpr_active/_typing.py
thermoextrap/gpr_active/active_utils.py
thermoextrap/gpr_active/gp_models.py
thermoextrap/gpr_active/ig_active.py
thermoextrap/gpr_active/sine_active.py
thermoextrap-1.0.0.dist-info/METADATA
thermoextrap-1.0.0.dist-info/WHEEL
thermoextrap-1.0.0.dist-info/licenses/LICENSE
thermoextrap-1.0.0.dist-info/RECORD
