Metadata-Version: 2.4
Name: thermoextrap
Version: 1.0.0
Summary: Thermodynamic extrapolation
Project-URL: Documentation, https://pages.nist.gov/thermoextrap/
Project-URL: Homepage, https://github.com/usnistgov/thermoextrap
Author-email: Jacob Monroe <jacob.monroe@nist.gov>, William Krekelberg <wpk@nist.gov>
License-Expression: NIST-PD
License-File: LICENSE
Keywords: thermoextrap
Classifier: Development Status :: 2 - Pre-Alpha
Classifier: Intended Audience :: Science/Research
Classifier: Operating System :: OS Independent
Classifier: Programming Language :: Python
Classifier: Programming Language :: Python :: 3 :: Only
Classifier: Programming Language :: Python :: 3.9
Classifier: Programming Language :: Python :: 3.10
Classifier: Programming Language :: Python :: 3.11
Classifier: Programming Language :: Python :: 3.12
Classifier: Topic :: Scientific/Engineering
Requires-Python: >=3.9
Requires-Dist: attrs>=24.1.0
Requires-Dist: cmomy>=1.0.1
Requires-Dist: dm-tree
Requires-Dist: lazy-loader
Requires-Dist: module-utilities[inherit]>=0.11.0
Requires-Dist: numba>=0.60.0
Requires-Dist: numpy>=1.26.0
Requires-Dist: packaging
Requires-Dist: scipy
Requires-Dist: sympy
Requires-Dist: xarray>=2024.7.0
Provides-Extra: accel
Requires-Dist: bottleneck; extra == 'accel'
Provides-Extra: all
Requires-Dist: bottleneck; extra == 'all'
Requires-Dist: dask[complete]; extra == 'all'
Requires-Dist: gpflow>=2.6.0; extra == 'all'
Requires-Dist: matplotlib; extra == 'all'
Requires-Dist: pymbar[jax]>=4.0; extra == 'all'
Requires-Dist: tensorflow-probability[tf]~=0.24.0; extra == 'all'
Requires-Dist: tensorflow>=2.13; extra == 'all'
Provides-Extra: gpr
Requires-Dist: gpflow>=2.6.0; extra == 'gpr'
Requires-Dist: tensorflow-probability[tf]~=0.24.0; extra == 'gpr'
Requires-Dist: tensorflow>=2.13; extra == 'gpr'
Provides-Extra: mbar
Requires-Dist: pymbar[jax]>=4.0; extra == 'mbar'
Provides-Extra: openmm
Requires-Dist: openmm; extra == 'openmm'
Provides-Extra: parallel
Requires-Dist: dask[complete]; extra == 'parallel'
Provides-Extra: viz
Requires-Dist: matplotlib; extra == 'viz'
